foxbobbyMCP/__init__.py
foxbobbyMCP/__main__.py
foxbobbymcp-0.1.0.dist-info/licenses/LICENSE
foxbobbymcp-0.1.0.dist-info/METADATA
foxbobbymcp-0.1.0.dist-info/WHEEL
foxbobbymcp-0.1.0.dist-info/entry_points.txt
foxbobbymcp-0.1.0.dist-info/top_level.txt
foxbobbymcp-0.1.0.dist-info/RECORD
